{
    "DefaultSkills": {
        "nikutai": [
            {
                "status": "nikutai",
                "exp": 0,
                "dice": 0,
                "other": 0,
                "name": "白兵",
                "memo": "",
                "perExp": 2
            },
            {
                "status": "nikutai",
                "exp": 0,
                "dice": 0,
                "other": 0,
                "name": "回避",
                "memo": "",
                "perExp": 2
            },
            {
                "status": "nikutai",
                "exp": 0,
                "dice": 0,
                "other": 0,
                "name": "",
                "memo": "",
                "perExp": 1
            }
        ],
        "kankaku": [
            {
                "status": "kankaku",
                "exp": 0,
                "dice": 0,
                "other": 0,
                "name": "射撃",
                "memo": "",
                "perExp": 2
            },
            {
                "status": "kankaku",
                "exp": 0,
                "dice": 0,
                "other": 0,
                "name": "知覚",
                "memo": "",
                "perExp": 2
            },
            {
                "status": "kankaku",
                "exp": 0,
                "dice": 0,
                "other": 0,
                "name": "",
                "memo": "",
                "perExp": 1
            }
        ],
        "seishin": [
            {
                "status": "seishin",
                "exp": 0,
                "dice": 0,
                "other": 0,
                "name": "RC",
                "memo": "",
                "perExp": 2
            },
            {
                "status": "seishin",
                "exp": 0,
                "dice": 0,
                "other": 0,
                "name": "意思",
                "memo": "",
                "perExp": 2
            },
            {
                "status": "seishin",
                "exp": 0,
                "dice": 0,
                "other": 0,
                "name": "",
                "memo": "",
                "perExp": 1
            }
        ],
        "syakai": [
            {
                "status": "syakai",
                "exp": 0,
                "dice": 0,
                "other": 0,
                "name": "交渉",
                "memo": "",
                "perExp": 2
            },
            {
                "status": "syakai",
                "exp": 0,
                "dice": 0,
                "other": 0,
                "name": "調達",
                "memo": "",
                "perExp": 2
            },
            {
                "status": "syakai",
                "exp": 0,
                "dice": 0,
                "other": 0,
                "name": "",
                "memo": "",
                "perExp": 1
            }
        ]
    },
    "EmptyRoyce": {
        "type": "-",
        "subject": "",
        "positive": "",
        "negative": "",
        "memo": ""
    },
    "DefaultCombo": {
        "ids": [],
        "stackable": {
            "attack": {
                "value": 0,
                "scale": 0,
                "lv": 0,
                "valueDice": 0,
                "scaleDice": 0,
                "plus": true,
                "showValue": true,
                "enable": false
            },
            "damageUp": {
                "value": 0,
                "scale": 0,
                "lv": 0,
                "valueDice": 0,
                "scaleDice": 0,
                "plus": true,
                "showValue": true,
                "enable": false
            },
            "heal": {
                "value": 0,
                "scale": 0,
                "lv": 0,
                "valueDice": 0,
                "scaleDice": 0,
                "plus": true,
                "showValue": true,
                "enable": false
            },
            "guard": {
                "value": 0,
                "scale": 0,
                "lv": 0,
                "valueDice": 0,
                "scaleDice": 0,
                "plus": true,
                "showValue": true,
                "enable": false
            },
            "armor": {
                "value": 0,
                "scale": 0,
                "lv": 0,
                "valueDice": 0,
                "scaleDice": 0,
                "plus": true,
                "showValue": true,
                "enable": false
            },
            "damageDown": {
                "value": 0,
                "scale": 0,
                "lv": 0,
                "valueDice": 0,
                "scaleDice": 0,
                "plus": true,
                "showValue": true,
                "enable": false
            },
            "hit": {
                "value": 0,
                "scale": 0,
                "lv": 0,
                "valueDice": 0,
                "scaleDice": 0,
                "plus": true,
                "showValue": true,
                "enable": false
            },
            "critical": {
                "value": 0,
                "scale": 0,
                "lv": 0,
                "valueDice": 0,
                "scaleDice": 0,
                "plus": true,
                "showValue": true,
                "enable": false
            }
        },
        "aggregate": {
            "attack": {
                "value": 0,
                "scale": 0,
                "lv": 0,
                "valueDice": 0,
                "scaleDice": 0,
                "plus": true,
                "showValue": true,
                "enable": false
            },
            "damageUp": {
                "value": 0,
                "scale": 0,
                "lv": 0,
                "valueDice": 0,
                "scaleDice": 0,
                "plus": true,
                "showValue": true,
                "enable": false
            },
            "heal": {
                "value": 0,
                "scale": 0,
                "lv": 0,
                "valueDice": 0,
                "scaleDice": 0,
                "plus": true,
                "showValue": true,
                "enable": false
            },
            "guard": {
                "value": 0,
                "scale": 0,
                "lv": 0,
                "valueDice": 0,
                "scaleDice": 0,
                "plus": true,
                "showValue": true,
                "enable": false
            },
            "armor": {
                "value": 0,
                "scale": 0,
                "lv": 0,
                "valueDice": 0,
                "scaleDice": 0,
                "plus": true,
                "showValue": true,
                "enable": false
            },
            "damageDown": {
                "value": 0,
                "scale": 0,
                "lv": 0,
                "valueDice": 0,
                "scaleDice": 0,
                "plus": true,
                "showValue": true,
                "enable": false
            },
            "hit": {
                "value": 0,
                "scale": 0,
                "lv": 0,
                "valueDice": 0,
                "scaleDice": 0,
                "plus": true,
                "showValue": true,
                "enable": false
            },
            "critical": {
                "value": 0,
                "scale": 0,
                "lv": 0,
                "valueDice": 0,
                "scaleDice": 0,
                "plus": true,
                "showValue": true,
                "enable": false
            }
        },
        "name": "",
        "timigng": "",
        "skill": "",
        "difficult": "",
        "sinsyoku": "",
        "limitation": "",
        "limitationCount": "",
        "target": "",
        "range": "",
        "memo": "",
        "enable": true
    },
    "DefaultItem": {
        "id": 0,
        "name": "",
        "memo": "",
        "exp": 0,
        "cost": 0,
        "enable": true,
        "type": "",
        "status": "owned"
    },
    "DefaultWeapon": {
        "id": 0,
        "skill": "",
        "range": "",
        "name": "",
        "memo": "",
        "exp": 0,
        "cost": 0,
        "enable": true,
        "type": "",
        "status": "equipped",
        "effectLv": 0,
        "attack": {
            "value": 0,
            "scale": 0,
            "lv": 0
        },
        "guard": {
            "value": 0,
            "scale": 0,
            "lv": 0
        },
        "hit": {
            "value": 0,
            "scale": 0,
            "lv": 0
        }
    },
    "DefaultArmor": {
        "id": 0,
        "name": "",
        "memo": "",
        "exp": 0,
        "cost": 0,
        "enable": true,
        "type": "",
        "status": "equipped",
        "effectLv": 0,
        "initiative": 0,
        "dodge": 0,
        "armor": {
            "value": 0,
            "scale": 0,
            "lv": 0
        }
    },
    "BaseSyndromes": [
        {
            "name": "選択してください",
            "status": {
                "nikutai": 0,
                "kankaku": 0,
                "seishin": 0,
                "syakai": 0
            }
        },
        {
            "name": "エンジェルハイロウ",
            "status": {
                "nikutai": 0,
                "kankaku": 3,
                "seishin": 1,
                "syakai": 0
            }
        },
        {
            "name": "バロール",
            "status": {
                "nikutai": 0,
                "kankaku": 1,
                "seishin": 2,
                "syakai": 1
            }
        },
        {
            "name": "ブラックドッグ",
            "status": {
                "nikutai": 2,
                "kankaku": 1,
                "seishin": 1,
                "syakai": 0
            }
        },
        {
            "name": "ブラムストーカー",
            "status": {
                "nikutai": 1,
                "kankaku": 2,
                "seishin": 1,
                "syakai": 0
            }
        },
        {
            "name": "キュマイラ",
            "status": {
                "nikutai": 3,
                "kankaku": 0,
                "seishin": 0,
                "syakai": 1
            }
        },
        {
            "name": "エグザイル",
            "status": {
                "nikutai": 2,
                "kankaku": 1,
                "seishin": 0,
                "syakai": 1
            }
        },
        {
            "name": "ハヌマーン",
            "status": {
                "nikutai": 1,
                "kankaku": 1,
                "seishin": 1,
                "syakai": 1
            }
        },
        {
            "name": "モルフェウス",
            "status": {
                "nikutai": 1,
                "kankaku": 2,
                "seishin": 0,
                "syakai": 1
            }
        },
        {
            "name": "ノイマン",
            "status": {
                "nikutai": 0,
                "kankaku": 0,
                "seishin": 3,
                "syakai": 1
            }
        },
        {
            "name": "オルクス",
            "status": {
                "nikutai": 0,
                "kankaku": 1,
                "seishin": 1,
                "syakai": 1
            }
        },
        {
            "name": "ソラリス",
            "status": {
                "nikutai": 0,
                "kankaku": 0,
                "seishin": 1,
                "syakai": 3
            }
        },
        {
            "name": "ウロボロス",
            "status": {
                "nikutai": 1,
                "kankaku": 1,
                "seishin": 2,
                "syakai": 0
            }
        },
        {
            "name": "アザトース",
            "status": {
                "nikutai": 1,
                "kankaku": 0,
                "seishin": 3,
                "syakai": 0
            }
        }
    ],
    "Default": {
        "profile": {
            "name": "",
            "age": "",
            "codeName": "",
            "player": "",
            "sexuality": "",
            "bloodType": "",
            "zodiac": "",
            "height": "",
            "weight": ""
        },
        "mainStatuses": {
            "syndrome1": {
                "name": "選択してください",
                "status": {
                    "nikutai": 0,
                    "kankaku": 0,
                    "seishin": 0,
                    "syakai": 0
                }
            },
            "syndrome2": {
                "name": "選択してください",
                "status": {
                    "nikutai": 0,
                    "kankaku": 0,
                    "seishin": 0,
                    "syakai": 0
                }
            },
            "optionalSyndrome": {
                "name": "選択してください",
                "status": {
                    "nikutai": 0,
                    "kankaku": 0,
                    "seishin": 0,
                    "syakai": 0
                }
            },
            "works": {
                "name": "",
                "status": {
                    "nikutai": 0,
                    "kankaku": 0,
                    "seishin": 0,
                    "syakai": 0
                }
            },
            "byExp": {
                "nikutai": 0,
                "kankaku": 0,
                "seishin": 0,
                "syakai": 0
            },
            "droyce": {
                "nikutai": 0,
                "kankaku": 0,
                "seishin": 0,
                "syakai": 0
            },
            "other": {
                "nikutai": 0,
                "kankaku": 0,
                "seishin": 0,
                "syakai": 0
            }
        },
        "subStatuses": [
            {
                "maxHp": 0,
                "zyoubi": 0,
                "zaisan": 0,
                "initiative": 0,
                "move": 0,
                "maxMove": 0,
                "shinsyoku": 0
            },
            {
                "maxHp": 0,
                "zyoubi": 0,
                "zaisan": 0,
                "initiative": 0,
                "move": 0,
                "maxMove": 0,
                "shinsyoku": 0
            },
            {
                "maxHp": 0,
                "zyoubi": 0,
                "zaisan": 0,
                "initiative": 0,
                "move": 0,
                "maxMove": 0,
                "shinsyoku": 0
            }
        ],
        "lifePaths": {
            "syutuji": {
                "name": "",
                "subject": "",
                "memo": ""
            },
            "keiken": {
                "name": "",
                "subject": "",
                "memo": ""
            },
            "kaikou": {
                "name": "",
                "subject": "",
                "memo": ""
            },
            "kakusei": {
                "name": "",
                "subject": "",
                "memo": ""
            },
            "syoudou": {
                "name": "",
                "subject": "",
                "memo": ""
            }
        },
        "skills": {
            "nikutai": [
                {
                    "status": "nikutai",
                    "exp": 0,
                    "dice": 0,
                    "other": 0,
                    "name": "白兵",
                    "memo": "",
                    "perExp": 2
                },
                {
                    "status": "nikutai",
                    "exp": 0,
                    "dice": 0,
                    "other": 0,
                    "name": "回避",
                    "memo": "",
                    "perExp": 2
                },
                {
                    "status": "nikutai",
                    "exp": 0,
                    "dice": 0,
                    "other": 0,
                    "name": "",
                    "memo": "",
                    "perExp": 1
                }
            ],
            "kankaku": [
                {
                    "status": "kankaku",
                    "exp": 0,
                    "dice": 0,
                    "other": 0,
                    "name": "射撃",
                    "memo": "",
                    "perExp": 2
                },
                {
                    "status": "kankaku",
                    "exp": 0,
                    "dice": 0,
                    "other": 0,
                    "name": "知覚",
                    "memo": "",
                    "perExp": 2
                },
                {
                    "status": "kankaku",
                    "exp": 0,
                    "dice": 0,
                    "other": 0,
                    "name": "",
                    "memo": "",
                    "perExp": 1
                }
            ],
            "seishin": [
                {
                    "status": "seishin",
                    "exp": 0,
                    "dice": 0,
                    "other": 0,
                    "name": "RC",
                    "memo": "",
                    "perExp": 2
                },
                {
                    "status": "seishin",
                    "exp": 0,
                    "dice": 0,
                    "other": 0,
                    "name": "意思",
                    "memo": "",
                    "perExp": 2
                },
                {
                    "status": "seishin",
                    "exp": 0,
                    "dice": 0,
                    "other": 0,
                    "name": "",
                    "memo": "",
                    "perExp": 1
                }
            ],
            "syakai": [
                {
                    "status": "syakai",
                    "exp": 0,
                    "dice": 0,
                    "other": 0,
                    "name": "交渉",
                    "memo": "",
                    "perExp": 2
                },
                {
                    "status": "syakai",
                    "exp": 0,
                    "dice": 0,
                    "other": 0,
                    "name": "調達",
                    "memo": "",
                    "perExp": 2
                },
                {
                    "status": "syakai",
                    "exp": 0,
                    "dice": 0,
                    "other": 0,
                    "name": "",
                    "memo": "",
                    "perExp": 1
                }
            ]
        },
        "royces": [
            {
                "type": "-",
                "subject": "",
                "positive": "",
                "negative": "",
                "memo": "",
                "titus": false
            },
            {
                "type": "-",
                "subject": "",
                "positive": "",
                "negative": "",
                "memo": "",
                "titus": false
            },
            {
                "type": "-",
                "subject": "",
                "positive": "",
                "negative": "",
                "memo": "",
                "titus": false
            },
            {
                "type": "-",
                "subject": "",
                "positive": "",
                "negative": "",
                "memo": "",
                "titus": false
            },
            {
                "type": "-",
                "subject": "",
                "positive": "",
                "negative": "",
                "memo": "",
                "titus": false
            },
            {
                "type": "-",
                "subject": "",
                "positive": "",
                "negative": "",
                "memo": "",
                "titus": false
            },
            {
                "type": "-",
                "subject": "",
                "positive": "",
                "negative": "",
                "memo": "",
                "titus": false
            }
        ],
        "effects": [
            {
                "id": 1,
                "type": "normal",
                "name": "コンセントレイト",
                "lv": 2,
                "timigng": "メジャー",
                "skill": "ｼﾝﾄﾞﾛｰﾑ",
                "difficult": "",
                "target": "-",
                "range": "-",
                "sinsyoku": "2",
                "limitation": "",
                "limitationCount": "",
                "stackable": {
                    "attack": {
                        "value": 0,
                        "scale": 0,
                        "lv": 0,
                        "valueDice": 0,
                        "scaleDice": 0,
                        "plus": true,
                        "showValue": true,
                        "enable": false
                    },
                    "damageUp": {
                        "value": 0,
                        "scale": 0,
                        "lv": 0,
                        "valueDice": 0,
                        "scaleDice": 0,
                        "plus": true,
                        "showValue": true,
                        "enable": false
                    },
                    "heal": {
                        "value": 0,
                        "scale": 0,
                        "lv": 0,
                        "valueDice": 0,
                        "scaleDice": 0,
                        "plus": true,
                        "showValue": true,
                        "enable": false
                    },
                    "guard": {
                        "value": 0,
                        "scale": 0,
                        "lv": 0,
                        "valueDice": 0,
                        "scaleDice": 0,
                        "plus": true,
                        "showValue": true,
                        "enable": false
                    },
                    "armor": {
                        "value": 0,
                        "scale": 0,
                        "lv": 0,
                        "valueDice": 0,
                        "scaleDice": 0,
                        "plus": true,
                        "showValue": true,
                        "enable": false
                    },
                    "damageDown": {
                        "value": 0,
                        "scale": 0,
                        "lv": 0,
                        "valueDice": 0,
                        "scaleDice": 0,
                        "plus": true,
                        "showValue": true,
                        "enable": false
                    },
                    "hit": {
                        "value": 0,
                        "scale": 0,
                        "lv": 0,
                        "valueDice": 0,
                        "scaleDice": 0,
                        "plus": true,
                        "showValue": true,
                        "enable": false
                    },
                    "critical": {
                        "value": 0,
                        "scale": 1,
                        "lv": 0,
                        "valueDice": 0,
                        "scaleDice": 0,
                        "plus": false,
                        "showValue": true,
                        "enable": true
                    }
                },
                "memo": "C値-1",
                "enable": true
            }
        ],
        "combos": [],
        "items": [],
        "weapons": [],
        "armors": [],
        "memo": "",
        "currentId": 10
    }
}
